{
  "body": {
    "family": {
      "value": [
        "Diatype",
        "Space Grotesk Frontify"
      ],
      "attributes": {
        "category": "font",
        "type": "family",
        "tailwind-name": "body-family"
      },
      "filePath": "/Users/noah.waldner/dev/frontify/fondue/packages/tokens/src/tokens/alias.body.ts",
      "isSource": true,
      "original": {
        "value": [
          "{font.diatype.value}",
          "{font.space-grotesk.value}"
        ],
        "attributes": {
          "category": "font",
          "type": "family"
        }
      },
      "name": "body-family",
      "path": [
        "body",
        "family"
      ]
    },
    "family-stack": {
      "value": [
        [
          "Diatype",
          "Space Grotesk Frontify"
        ],
        "Arial",
        "-apple-system",
        "BlinkMacSystemFont",
        "Segoe UI",
        "Roboto",
        "Helvetica",
        "sans-serif",
        "Apple Color Emoji",
        "Segoe UI Emoji",
        "Segoe UI Symbol"
      ],
      "attributes": {
        "category": "font",
        "type": "family",
        "tailwind-name": "body-family-stack"
      },
      "filePath": "/Users/noah.waldner/dev/frontify/fondue/packages/tokens/src/tokens/alias.body.ts",
      "isSource": true,
      "original": {
        "value": [
          "{body.family.value}",
          "Arial",
          "-apple-system",
          "BlinkMacSystemFont",
          "Segoe UI",
          "Roboto",
          "Helvetica",
          "sans-serif",
          "Apple Color Emoji",
          "Segoe UI Emoji",
          "Segoe UI Symbol"
        ],
        "attributes": {
          "category": "font",
          "type": "family"
        }
      },
      "name": "body-family-stack",
      "path": [
        "body",
        "family-stack"
      ]
    },
    "weight-name": {
      "value": "Regular",
      "attributes": {
        "category": "font",
        "type": "name",
        "tailwind-name": "body-weight-name"
      },
      "filePath": "/Users/noah.waldner/dev/frontify/fondue/packages/tokens/src/tokens/alias.body.ts",
      "isSource": true,
      "original": {
        "value": "{font.space-grotesk-regular-weight-name.value}",
        "attributes": {
          "category": "font",
          "type": "name"
        }
      },
      "name": "body-weight-name",
      "path": [
        "body",
        "weight-name"
      ]
    },
    "weight-number": {
      "value": 400,
      "attributes": {
        "category": "font",
        "type": "weight",
        "tailwind-name": "body-weight-number"
      },
      "filePath": "/Users/noah.waldner/dev/frontify/fondue/packages/tokens/src/tokens/alias.body.ts",
      "isSource": true,
      "original": {
        "value": "{font.space-grotesk-regular-weight-number.value}",
        "attributes": {
          "category": "font",
          "type": "weight"
        }
      },
      "name": "body-weight-number",
      "path": [
        "body",
        "weight-number"
      ]
    },
    "weight-strong-name": {
      "value": "Medium",
      "attributes": {
        "category": "font",
        "type": "name",
        "tailwind-name": "body-weight-strong-name"
      },
      "filePath": "/Users/noah.waldner/dev/frontify/fondue/packages/tokens/src/tokens/alias.body.ts",
      "isSource": true,
      "original": {
        "value": "{font.space-grotesk-medium-weight-name.value}",
        "attributes": {
          "category": "font",
          "type": "name"
        }
      },
      "name": "body-weight-strong-name",
      "path": [
        "body",
        "weight-strong-name"
      ]
    },
    "weight-strong-number": {
      "value": 500,
      "attributes": {
        "category": "font",
        "type": "weight",
        "tailwind-name": "body-weight-strong-number"
      },
      "filePath": "/Users/noah.waldner/dev/frontify/fondue/packages/tokens/src/tokens/alias.body.ts",
      "isSource": true,
      "original": {
        "value": "{font.space-grotesk-medium-weight-number.value}",
        "attributes": {
          "category": "font",
          "type": "weight"
        }
      },
      "name": "body-weight-strong-number",
      "path": [
        "body",
        "weight-strong-number"
      ]
    },
    "weight-x-strong-name": {
      "value": "Bold",
      "attributes": {
        "category": "font",
        "type": "name",
        "tailwind-name": "body-weight-x-strong-name"
      },
      "filePath": "/Users/noah.waldner/dev/frontify/fondue/packages/tokens/src/tokens/alias.body.ts",
      "isSource": true,
      "original": {
        "value": "{font.space-grotesk-bold-weight-name.value}",
        "attributes": {
          "category": "font",
          "type": "name"
        }
      },
      "name": "body-weight-x-strong-name",
      "path": [
        "body",
        "weight-x-strong-name"
      ]
    },
    "weight-x-strong-number": {
      "value": 700,
      "attributes": {
        "category": "font",
        "type": "weight",
        "tailwind-name": "body-weight-x-strong-number"
      },
      "filePath": "/Users/noah.waldner/dev/frontify/fondue/packages/tokens/src/tokens/alias.body.ts",
      "isSource": true,
      "original": {
        "value": "{font.space-grotesk-bold-weight-number.value}",
        "attributes": {
          "category": "font",
          "type": "weight"
        }
      },
      "name": "body-weight-x-strong-number",
      "path": [
        "body",
        "weight-x-strong-number"
      ]
    },
    "size-x-small": {
      "value": "0.75rem",
      "attributes": {
        "category": "size",
        "type": "font",
        "tailwind-name": "body-size-x-small"
      },
      "filePath": "/Users/noah.waldner/dev/frontify/fondue/packages/tokens/src/tokens/alias.body.ts",
      "isSource": true,
      "original": {
        "value": 0.75,
        "attributes": {
          "category": "size",
          "type": "font"
        }
      },
      "name": "body-size-x-small",
      "path": [
        "body",
        "size-x-small"
      ]
    },
    "size-x-small-line-height": {
      "value": "1rem",
      "attributes": {
        "category": "size",
        "type": "lineHeight",
        "tailwind-name": "body-size-x-small-line-height"
      },
      "filePath": "/Users/noah.waldner/dev/frontify/fondue/packages/tokens/src/tokens/alias.body.ts",
      "isSource": true,
      "original": {
        "value": 1,
        "attributes": {
          "category": "size",
          "type": "lineHeight"
        }
      },
      "name": "body-size-x-small-line-height",
      "path": [
        "body",
        "size-x-small-line-height"
      ]
    },
    "size-small": {
      "value": "0.813rem",
      "attributes": {
        "category": "size",
        "type": "font",
        "tailwind-name": "body-size-small"
      },
      "filePath": "/Users/noah.waldner/dev/frontify/fondue/packages/tokens/src/tokens/alias.body.ts",
      "isSource": true,
      "original": {
        "value": 0.813,
        "attributes": {
          "category": "size",
          "type": "font"
        }
      },
      "name": "body-size-small",
      "path": [
        "body",
        "size-small"
      ]
    },
    "size-small-line-height": {
      "value": "1rem",
      "attributes": {
        "category": "size",
        "type": "lineHeight",
        "tailwind-name": "body-size-small-line-height"
      },
      "filePath": "/Users/noah.waldner/dev/frontify/fondue/packages/tokens/src/tokens/alias.body.ts",
      "isSource": true,
      "original": {
        "value": 1,
        "attributes": {
          "category": "size",
          "type": "lineHeight"
        }
      },
      "name": "body-size-small-line-height",
      "path": [
        "body",
        "size-small-line-height"
      ]
    },
    "size-medium": {
      "value": "0.875rem",
      "attributes": {
        "category": "size",
        "type": "font",
        "tailwind-name": "body-size-medium"
      },
      "filePath": "/Users/noah.waldner/dev/frontify/fondue/packages/tokens/src/tokens/alias.body.ts",
      "isSource": true,
      "original": {
        "value": 0.875,
        "attributes": {
          "category": "size",
          "type": "font"
        }
      },
      "name": "body-size-medium",
      "path": [
        "body",
        "size-medium"
      ]
    },
    "size-medium-line-height": {
      "value": "1.125rem",
      "attributes": {
        "category": "size",
        "type": "lineHeight",
        "tailwind-name": "body-size-medium-line-height"
      },
      "filePath": "/Users/noah.waldner/dev/frontify/fondue/packages/tokens/src/tokens/alias.body.ts",
      "isSource": true,
      "original": {
        "value": 1.125,
        "attributes": {
          "category": "size",
          "type": "lineHeight"
        }
      },
      "name": "body-size-medium-line-height",
      "path": [
        "body",
        "size-medium-line-height"
      ]
    },
    "size-large": {
      "value": "1rem",
      "attributes": {
        "category": "size",
        "type": "font",
        "tailwind-name": "body-size-large"
      },
      "filePath": "/Users/noah.waldner/dev/frontify/fondue/packages/tokens/src/tokens/alias.body.ts",
      "isSource": true,
      "original": {
        "value": 1,
        "attributes": {
          "category": "size",
          "type": "font"
        }
      },
      "name": "body-size-large",
      "path": [
        "body",
        "size-large"
      ]
    },
    "size-large-line-height": {
      "value": "1.25rem",
      "attributes": {
        "category": "size",
        "type": "lineHeight",
        "tailwind-name": "body-size-large-line-height"
      },
      "filePath": "/Users/noah.waldner/dev/frontify/fondue/packages/tokens/src/tokens/alias.body.ts",
      "isSource": true,
      "original": {
        "value": 1.25,
        "attributes": {
          "category": "size",
          "type": "lineHeight"
        }
      },
      "name": "body-size-large-line-height",
      "path": [
        "body",
        "size-large-line-height"
      ]
    },
    "x-small": {
      "value": {
        "fontFamily": [
          "Diatype",
          "Space Grotesk Frontify"
        ],
        "fontSize": "0.75rem",
        "lineHeight": "1rem",
        "fontWeight": "Regular"
      },
      "attributes": {
        "category": "font",
        "type": "style",
        "target": "figma",
        "tailwind-name": "body-x-small"
      },
      "filePath": "/Users/noah.waldner/dev/frontify/fondue/packages/tokens/src/tokens/alias.body.ts",
      "isSource": true,
      "original": {
        "value": {
          "fontFamily": "{body.family.value}",
          "fontSize": "{body.size-x-small.value}",
          "lineHeight": "{body.size-x-small-line-height.value}",
          "fontWeight": "{body.weight-name.value}"
        },
        "attributes": {
          "category": "font",
          "type": "style",
          "target": "figma"
        }
      },
      "name": "body-x-small",
      "path": [
        "body",
        "x-small"
      ]
    },
    "x-small-strong": {
      "value": {
        "fontFamily": [
          "Diatype",
          "Space Grotesk Frontify"
        ],
        "fontSize": "0.75rem",
        "lineHeight": "1rem",
        "fontWeight": "Medium"
      },
      "attributes": {
        "category": "font",
        "type": "style",
        "target": "figma",
        "tailwind-name": "body-x-small-strong"
      },
      "filePath": "/Users/noah.waldner/dev/frontify/fondue/packages/tokens/src/tokens/alias.body.ts",
      "isSource": true,
      "original": {
        "value": {
          "fontFamily": "{body.family.value}",
          "fontSize": "{body.size-x-small.value}",
          "lineHeight": "{body.size-x-small-line-height.value}",
          "fontWeight": "{body.weight-strong-name.value}"
        },
        "attributes": {
          "category": "font",
          "type": "style",
          "target": "figma"
        }
      },
      "name": "body-x-small-strong",
      "path": [
        "body",
        "x-small-strong"
      ]
    },
    "x-small-x-strong": {
      "value": {
        "fontFamily": [
          "Diatype",
          "Space Grotesk Frontify"
        ],
        "fontSize": "0.75rem",
        "lineHeight": "1rem",
        "fontWeight": "Bold"
      },
      "attributes": {
        "category": "font",
        "type": "style",
        "target": "figma",
        "tailwind-name": "body-x-small-x-strong"
      },
      "filePath": "/Users/noah.waldner/dev/frontify/fondue/packages/tokens/src/tokens/alias.body.ts",
      "isSource": true,
      "original": {
        "value": {
          "fontFamily": "{body.family.value}",
          "fontSize": "{body.size-x-small.value}",
          "lineHeight": "{body.size-x-small-line-height.value}",
          "fontWeight": "{body.weight-x-strong-name.value}"
        },
        "attributes": {
          "category": "font",
          "type": "style",
          "target": "figma"
        }
      },
      "name": "body-x-small-x-strong",
      "path": [
        "body",
        "x-small-x-strong"
      ]
    },
    "small": {
      "value": {
        "fontFamily": [
          "Diatype",
          "Space Grotesk Frontify"
        ],
        "fontSize": "0.813rem",
        "lineHeight": "1rem",
        "fontWeight": "Regular"
      },
      "attributes": {
        "category": "font",
        "type": "style",
        "target": "figma",
        "tailwind-name": "body-small"
      },
      "filePath": "/Users/noah.waldner/dev/frontify/fondue/packages/tokens/src/tokens/alias.body.ts",
      "isSource": true,
      "original": {
        "value": {
          "fontFamily": "{body.family.value}",
          "fontSize": "{body.size-small.value}",
          "lineHeight": "{body.size-small-line-height.value}",
          "fontWeight": "{body.weight-name.value}"
        },
        "attributes": {
          "category": "font",
          "type": "style",
          "target": "figma"
        }
      },
      "name": "body-small",
      "path": [
        "body",
        "small"
      ]
    },
    "small-strong": {
      "value": {
        "fontFamily": [
          "Diatype",
          "Space Grotesk Frontify"
        ],
        "fontSize": "0.813rem",
        "lineHeight": "1rem",
        "fontWeight": "Medium"
      },
      "attributes": {
        "category": "font",
        "type": "style",
        "target": "figma",
        "tailwind-name": "body-small-strong"
      },
      "filePath": "/Users/noah.waldner/dev/frontify/fondue/packages/tokens/src/tokens/alias.body.ts",
      "isSource": true,
      "original": {
        "value": {
          "fontFamily": "{body.family.value}",
          "fontSize": "{body.size-small.value}",
          "lineHeight": "{body.size-small-line-height.value}",
          "fontWeight": "{body.weight-strong-name.value}"
        },
        "attributes": {
          "category": "font",
          "type": "style",
          "target": "figma"
        }
      },
      "name": "body-small-strong",
      "path": [
        "body",
        "small-strong"
      ]
    },
    "small-x-strong": {
      "value": {
        "fontFamily": [
          "Diatype",
          "Space Grotesk Frontify"
        ],
        "fontSize": "0.813rem",
        "lineHeight": "1rem",
        "fontWeight": "Bold"
      },
      "attributes": {
        "category": "font",
        "type": "style",
        "target": "figma",
        "tailwind-name": "body-small-x-strong"
      },
      "filePath": "/Users/noah.waldner/dev/frontify/fondue/packages/tokens/src/tokens/alias.body.ts",
      "isSource": true,
      "original": {
        "value": {
          "fontFamily": "{body.family.value}",
          "fontSize": "{body.size-small.value}",
          "lineHeight": "{body.size-small-line-height.value}",
          "fontWeight": "{body.weight-x-strong-name.value}"
        },
        "attributes": {
          "category": "font",
          "type": "style",
          "target": "figma"
        }
      },
      "name": "body-small-x-strong",
      "path": [
        "body",
        "small-x-strong"
      ]
    },
    "medium": {
      "value": {
        "fontFamily": [
          "Diatype",
          "Space Grotesk Frontify"
        ],
        "fontSize": "0.875rem",
        "lineHeight": "1.125rem",
        "fontWeight": "Regular"
      },
      "attributes": {
        "category": "font",
        "type": "style",
        "target": "figma",
        "tailwind-name": "body-medium"
      },
      "filePath": "/Users/noah.waldner/dev/frontify/fondue/packages/tokens/src/tokens/alias.body.ts",
      "isSource": true,
      "original": {
        "value": {
          "fontFamily": "{body.family.value}",
          "fontSize": "{body.size-medium.value}",
          "lineHeight": "{body.size-medium-line-height.value}",
          "fontWeight": "{body.weight-name.value}"
        },
        "attributes": {
          "category": "font",
          "type": "style",
          "target": "figma"
        }
      },
      "name": "body-medium",
      "path": [
        "body",
        "medium"
      ]
    },
    "medium-strong": {
      "value": {
        "fontFamily": [
          "Diatype",
          "Space Grotesk Frontify"
        ],
        "fontSize": "0.875rem",
        "lineHeight": "1.125rem",
        "fontWeight": "Medium"
      },
      "attributes": {
        "category": "font",
        "type": "style",
        "target": "figma",
        "tailwind-name": "body-medium-strong"
      },
      "filePath": "/Users/noah.waldner/dev/frontify/fondue/packages/tokens/src/tokens/alias.body.ts",
      "isSource": true,
      "original": {
        "value": {
          "fontFamily": "{body.family.value}",
          "fontSize": "{body.size-medium.value}",
          "lineHeight": "{body.size-medium-line-height.value}",
          "fontWeight": "{body.weight-strong-name.value}"
        },
        "attributes": {
          "category": "font",
          "type": "style",
          "target": "figma"
        }
      },
      "name": "body-medium-strong",
      "path": [
        "body",
        "medium-strong"
      ]
    },
    "medium-x-strong": {
      "value": {
        "fontFamily": [
          "Diatype",
          "Space Grotesk Frontify"
        ],
        "fontSize": "0.875rem",
        "lineHeight": "1.125rem",
        "fontWeight": "Bold"
      },
      "attributes": {
        "category": "font",
        "type": "style",
        "target": "figma",
        "tailwind-name": "body-medium-x-strong"
      },
      "filePath": "/Users/noah.waldner/dev/frontify/fondue/packages/tokens/src/tokens/alias.body.ts",
      "isSource": true,
      "original": {
        "value": {
          "fontFamily": "{body.family.value}",
          "fontSize": "{body.size-medium.value}",
          "lineHeight": "{body.size-medium-line-height.value}",
          "fontWeight": "{body.weight-x-strong-name.value}"
        },
        "attributes": {
          "category": "font",
          "type": "style",
          "target": "figma"
        }
      },
      "name": "body-medium-x-strong",
      "path": [
        "body",
        "medium-x-strong"
      ]
    },
    "large": {
      "value": {
        "fontFamily": [
          "Diatype",
          "Space Grotesk Frontify"
        ],
        "fontSize": "1rem",
        "lineHeight": "1.25rem",
        "fontWeight": "Regular"
      },
      "attributes": {
        "category": "font",
        "type": "style",
        "target": "figma",
        "tailwind-name": "body-large"
      },
      "filePath": "/Users/noah.waldner/dev/frontify/fondue/packages/tokens/src/tokens/alias.body.ts",
      "isSource": true,
      "original": {
        "value": {
          "fontFamily": "{body.family.value}",
          "fontSize": "{body.size-large.value}",
          "lineHeight": "{body.size-large-line-height.value}",
          "fontWeight": "{body.weight-name.value}"
        },
        "attributes": {
          "category": "font",
          "type": "style",
          "target": "figma"
        }
      },
      "name": "body-large",
      "path": [
        "body",
        "large"
      ]
    },
    "large-strong": {
      "value": {
        "fontFamily": [
          "Diatype",
          "Space Grotesk Frontify"
        ],
        "fontSize": "1rem",
        "lineHeight": "1.25rem",
        "fontWeight": "Medium"
      },
      "attributes": {
        "category": "font",
        "type": "style",
        "target": "figma",
        "tailwind-name": "body-large-strong"
      },
      "filePath": "/Users/noah.waldner/dev/frontify/fondue/packages/tokens/src/tokens/alias.body.ts",
      "isSource": true,
      "original": {
        "value": {
          "fontFamily": "{body.family.value}",
          "fontSize": "{body.size-large.value}",
          "lineHeight": "{body.size-large-line-height.value}",
          "fontWeight": "{body.weight-strong-name.value}"
        },
        "attributes": {
          "category": "font",
          "type": "style",
          "target": "figma"
        }
      },
      "name": "body-large-strong",
      "path": [
        "body",
        "large-strong"
      ]
    },
    "large-x-strong": {
      "value": {
        "fontFamily": [
          "Diatype",
          "Space Grotesk Frontify"
        ],
        "fontSize": "1rem",
        "lineHeight": "1.25rem",
        "fontWeight": "Bold"
      },
      "attributes": {
        "category": "font",
        "type": "style",
        "target": "figma",
        "tailwind-name": "body-large-x-strong"
      },
      "filePath": "/Users/noah.waldner/dev/frontify/fondue/packages/tokens/src/tokens/alias.body.ts",
      "isSource": true,
      "original": {
        "value": {
          "fontFamily": "{body.family.value}",
          "fontSize": "{body.size-large.value}",
          "lineHeight": "{body.size-large-line-height.value}",
          "fontWeight": "{body.weight-x-strong-name.value}"
        },
        "attributes": {
          "category": "font",
          "type": "style",
          "target": "figma"
        }
      },
      "name": "body-large-x-strong",
      "path": [
        "body",
        "large-x-strong"
      ]
    }
  },
  "code": {
    "family": {
      "value": "Menlo",
      "attributes": {
        "category": "font",
        "type": "family",
        "tailwind-name": "code-family"
      },
      "filePath": "/Users/noah.waldner/dev/frontify/fondue/packages/tokens/src/tokens/alias.code.ts",
      "isSource": true,
      "original": {
        "value": "{font.menlo.value}",
        "attributes": {
          "category": "font",
          "type": "family"
        }
      },
      "name": "code-family",
      "path": [
        "code",
        "family"
      ]
    },
    "family-stack": {
      "value": [
        "Menlo",
        "Courier",
        "monospace"
      ],
      "attributes": {
        "category": "font",
        "type": "family",
        "tailwind-name": "code-family-stack"
      },
      "filePath": "/Users/noah.waldner/dev/frontify/fondue/packages/tokens/src/tokens/alias.code.ts",
      "isSource": true,
      "original": {
        "value": [
          "{code.family.value}",
          "Courier",
          "monospace"
        ],
        "attributes": {
          "category": "font",
          "type": "family"
        }
      },
      "name": "code-family-stack",
      "path": [
        "code",
        "family-stack"
      ]
    },
    "weight-name": {
      "value": "Regular",
      "attributes": {
        "category": "font",
        "type": "name",
        "tailwind-name": "code-weight-name"
      },
      "filePath": "/Users/noah.waldner/dev/frontify/fondue/packages/tokens/src/tokens/alias.code.ts",
      "isSource": true,
      "original": {
        "value": "{font.menlo-regular-weight-name.value}",
        "attributes": {
          "category": "font",
          "type": "name"
        }
      },
      "name": "code-weight-name",
      "path": [
        "code",
        "weight-name"
      ]
    },
    "weight-number": {
      "value": "Regular",
      "attributes": {
        "category": "font",
        "type": "weight",
        "tailwind-name": "code-weight-number"
      },
      "filePath": "/Users/noah.waldner/dev/frontify/fondue/packages/tokens/src/tokens/alias.code.ts",
      "isSource": true,
      "original": {
        "value": "{font.menlo-regular-weight-name.value}",
        "attributes": {
          "category": "font",
          "type": "weight"
        }
      },
      "name": "code-weight-number",
      "path": [
        "code",
        "weight-number"
      ]
    },
    "weight-strong-name": {
      "value": "Bold",
      "attributes": {
        "category": "font",
        "type": "name",
        "tailwind-name": "code-weight-strong-name"
      },
      "filePath": "/Users/noah.waldner/dev/frontify/fondue/packages/tokens/src/tokens/alias.code.ts",
      "isSource": true,
      "original": {
        "value": "{font.menlo-bold-weight-name.value}",
        "attributes": {
          "category": "font",
          "type": "name"
        }
      },
      "name": "code-weight-strong-name",
      "path": [
        "code",
        "weight-strong-name"
      ]
    },
    "weight-strong-number": {
      "value": 700,
      "attributes": {
        "category": "font",
        "type": "weight",
        "tailwind-name": "code-weight-strong-number"
      },
      "filePath": "/Users/noah.waldner/dev/frontify/fondue/packages/tokens/src/tokens/alias.code.ts",
      "isSource": true,
      "original": {
        "value": "{font.menlo-bold-weight-number.value}",
        "attributes": {
          "category": "font",
          "type": "weight"
        }
      },
      "name": "code-weight-strong-number",
      "path": [
        "code",
        "weight-strong-number"
      ]
    },
    "size-small": {
      "value": "0.813rem",
      "attributes": {
        "category": "size",
        "type": "font",
        "tailwind-name": "code-size-small"
      },
      "filePath": "/Users/noah.waldner/dev/frontify/fondue/packages/tokens/src/tokens/alias.code.ts",
      "isSource": true,
      "original": {
        "value": 0.813,
        "attributes": {
          "category": "size",
          "type": "font"
        }
      },
      "name": "code-size-small",
      "path": [
        "code",
        "size-small"
      ]
    },
    "size-small-line-height": {
      "value": "1rem",
      "attributes": {
        "category": "size",
        "type": "lineHeight",
        "tailwind-name": "code-size-small-line-height"
      },
      "filePath": "/Users/noah.waldner/dev/frontify/fondue/packages/tokens/src/tokens/alias.code.ts",
      "isSource": true,
      "original": {
        "value": 1,
        "attributes": {
          "category": "size",
          "type": "lineHeight"
        }
      },
      "name": "code-size-small-line-height",
      "path": [
        "code",
        "size-small-line-height"
      ]
    },
    "size-medium": {
      "value": "0.875rem",
      "attributes": {
        "category": "size",
        "type": "font",
        "tailwind-name": "code-size-medium"
      },
      "filePath": "/Users/noah.waldner/dev/frontify/fondue/packages/tokens/src/tokens/alias.code.ts",
      "isSource": true,
      "original": {
        "value": 0.875,
        "attributes": {
          "category": "size",
          "type": "font"
        }
      },
      "name": "code-size-medium",
      "path": [
        "code",
        "size-medium"
      ]
    },
    "size-medium-line-height": {
      "value": "1rem",
      "attributes": {
        "category": "size",
        "type": "lineHeight",
        "tailwind-name": "code-size-medium-line-height"
      },
      "filePath": "/Users/noah.waldner/dev/frontify/fondue/packages/tokens/src/tokens/alias.code.ts",
      "isSource": true,
      "original": {
        "value": 1,
        "attributes": {
          "category": "size",
          "type": "lineHeight"
        }
      },
      "name": "code-size-medium-line-height",
      "path": [
        "code",
        "size-medium-line-height"
      ]
    },
    "size-large": {
      "value": "1rem",
      "attributes": {
        "category": "size",
        "type": "font",
        "tailwind-name": "code-size-large"
      },
      "filePath": "/Users/noah.waldner/dev/frontify/fondue/packages/tokens/src/tokens/alias.code.ts",
      "isSource": true,
      "original": {
        "value": 1,
        "attributes": {
          "category": "size",
          "type": "font"
        }
      },
      "name": "code-size-large",
      "path": [
        "code",
        "size-large"
      ]
    },
    "size-large-line-height": {
      "value": "1.25rem",
      "attributes": {
        "category": "size",
        "type": "lineHeight",
        "tailwind-name": "code-size-large-line-height"
      },
      "filePath": "/Users/noah.waldner/dev/frontify/fondue/packages/tokens/src/tokens/alias.code.ts",
      "isSource": true,
      "original": {
        "value": 1.25,
        "attributes": {
          "category": "size",
          "type": "lineHeight"
        }
      },
      "name": "code-size-large-line-height",
      "path": [
        "code",
        "size-large-line-height"
      ]
    },
    "small": {
      "value": {
        "fontFamily": "Menlo",
        "fontSize": "0.813rem",
        "lineHeight": "1rem",
        "fontWeight": "Regular"
      },
      "attributes": {
        "category": "font",
        "type": "style",
        "target": "figma",
        "tailwind-name": "code-small"
      },
      "filePath": "/Users/noah.waldner/dev/frontify/fondue/packages/tokens/src/tokens/alias.code.ts",
      "isSource": true,
      "original": {
        "value": {
          "fontFamily": "{code.family.value}",
          "fontSize": "{code.size-small.value}",
          "lineHeight": "{code.size-small-line-height.value}",
          "fontWeight": "{code.weight-name.value}"
        },
        "attributes": {
          "category": "font",
          "type": "style",
          "target": "figma"
        }
      },
      "name": "code-small",
      "path": [
        "code",
        "small"
      ]
    },
    "small-strong": {
      "value": {
        "fontFamily": "Menlo",
        "fontSize": "0.813rem",
        "lineHeight": "1rem",
        "fontWeight": "Bold"
      },
      "attributes": {
        "category": "font",
        "type": "style",
        "target": "figma",
        "tailwind-name": "code-small-strong"
      },
      "filePath": "/Users/noah.waldner/dev/frontify/fondue/packages/tokens/src/tokens/alias.code.ts",
      "isSource": true,
      "original": {
        "value": {
          "fontFamily": "{code.family.value}",
          "fontSize": "{code.size-small.value}",
          "lineHeight": "{code.size-small-line-height.value}",
          "fontWeight": "{code.weight-strong-name.value}"
        },
        "attributes": {
          "category": "font",
          "type": "style",
          "target": "figma"
        }
      },
      "name": "code-small-strong",
      "path": [
        "code",
        "small-strong"
      ]
    },
    "medium": {
      "value": {
        "fontFamily": "Menlo",
        "fontSize": "0.875rem",
        "lineHeight": "1rem",
        "fontWeight": "Regular"
      },
      "attributes": {
        "category": "font",
        "type": "style",
        "target": "figma",
        "tailwind-name": "code-medium"
      },
      "filePath": "/Users/noah.waldner/dev/frontify/fondue/packages/tokens/src/tokens/alias.code.ts",
      "isSource": true,
      "original": {
        "value": {
          "fontFamily": "{code.family.value}",
          "fontSize": "{code.size-medium.value}",
          "lineHeight": "{code.size-medium-line-height.value}",
          "fontWeight": "{code.weight-name.value}"
        },
        "attributes": {
          "category": "font",
          "type": "style",
          "target": "figma"
        }
      },
      "name": "code-medium",
      "path": [
        "code",
        "medium"
      ]
    },
    "medium-strong": {
      "value": {
        "fontFamily": "Menlo",
        "fontSize": "0.875rem",
        "lineHeight": "1rem",
        "fontWeight": "Bold"
      },
      "attributes": {
        "category": "font",
        "type": "style",
        "target": "figma",
        "tailwind-name": "code-medium-strong"
      },
      "filePath": "/Users/noah.waldner/dev/frontify/fondue/packages/tokens/src/tokens/alias.code.ts",
      "isSource": true,
      "original": {
        "value": {
          "fontFamily": "{code.family.value}",
          "fontSize": "{code.size-medium.value}",
          "lineHeight": "{code.size-medium-line-height.value}",
          "fontWeight": "{code.weight-strong-name.value}"
        },
        "attributes": {
          "category": "font",
          "type": "style",
          "target": "figma"
        }
      },
      "name": "code-medium-strong",
      "path": [
        "code",
        "medium-strong"
      ]
    },
    "large": {
      "value": {
        "fontFamily": "Menlo",
        "fontSize": "1rem",
        "lineHeight": "1.25rem",
        "fontWeight": "Regular"
      },
      "attributes": {
        "category": "font",
        "type": "style",
        "target": "figma",
        "tailwind-name": "code-large"
      },
      "filePath": "/Users/noah.waldner/dev/frontify/fondue/packages/tokens/src/tokens/alias.code.ts",
      "isSource": true,
      "original": {
        "value": {
          "fontFamily": "{code.family.value}",
          "fontSize": "{code.size-large.value}",
          "lineHeight": "{code.size-large-line-height.value}",
          "fontWeight": "{code.weight-name.value}"
        },
        "attributes": {
          "category": "font",
          "type": "style",
          "target": "figma"
        }
      },
      "name": "code-large",
      "path": [
        "code",
        "large"
      ]
    },
    "large-strong": {
      "value": {
        "fontFamily": "Menlo",
        "fontSize": "1rem",
        "lineHeight": "1.25rem",
        "fontWeight": "Bold"
      },
      "attributes": {
        "category": "font",
        "type": "style",
        "target": "figma",
        "tailwind-name": "code-large-strong"
      },
      "filePath": "/Users/noah.waldner/dev/frontify/fondue/packages/tokens/src/tokens/alias.code.ts",
      "isSource": true,
      "original": {
        "value": {
          "fontFamily": "{code.family.value}",
          "fontSize": "{code.size-large.value}",
          "lineHeight": "{code.size-large-line-height.value}",
          "fontWeight": "{code.weight-strong-name.value}"
        },
        "attributes": {
          "category": "font",
          "type": "style",
          "target": "figma"
        }
      },
      "name": "code-large-strong",
      "path": [
        "code",
        "large-strong"
      ]
    }
  },
  "heading": {
    "family": {
      "value": [
        "Diatype",
        "Space Grotesk Frontify"
      ],
      "attributes": {
        "category": "font",
        "type": "family",
        "tailwind-name": "heading-family"
      },
      "filePath": "/Users/noah.waldner/dev/frontify/fondue/packages/tokens/src/tokens/alias.heading.ts",
      "isSource": true,
      "original": {
        "value": "{body.family.value}",
        "attributes": {
          "category": "font",
          "type": "family"
        }
      },
      "name": "heading-family",
      "path": [
        "heading",
        "family"
      ]
    },
    "family-stack": {
      "value": [
        [
          "Diatype",
          "Space Grotesk Frontify"
        ],
        "Arial",
        "-apple-system",
        "BlinkMacSystemFont",
        "Segoe UI",
        "Roboto",
        "Helvetica",
        "sans-serif",
        "Apple Color Emoji",
        "Segoe UI Emoji",
        "Segoe UI Symbol"
      ],
      "attributes": {
        "category": "font",
        "type": "family",
        "tailwind-name": "heading-family-stack"
      },
      "filePath": "/Users/noah.waldner/dev/frontify/fondue/packages/tokens/src/tokens/alias.heading.ts",
      "isSource": true,
      "original": {
        "value": "{body.family-stack.value}",
        "attributes": {
          "category": "font",
          "type": "family"
        }
      },
      "name": "heading-family-stack",
      "path": [
        "heading",
        "family-stack"
      ]
    },
    "weight-name": {
      "value": "Medium",
      "attributes": {
        "category": "font",
        "type": "name",
        "tailwind-name": "heading-weight-name"
      },
      "filePath": "/Users/noah.waldner/dev/frontify/fondue/packages/tokens/src/tokens/alias.heading.ts",
      "isSource": true,
      "original": {
        "value": "{font.space-grotesk-medium-weight-name.value}",
        "attributes": {
          "category": "font",
          "type": "name"
        }
      },
      "name": "heading-weight-name",
      "path": [
        "heading",
        "weight-name"
      ]
    },
    "weight-number": {
      "value": 500,
      "attributes": {
        "category": "font",
        "type": "weight",
        "tailwind-name": "heading-weight-number"
      },
      "filePath": "/Users/noah.waldner/dev/frontify/fondue/packages/tokens/src/tokens/alias.heading.ts",
      "isSource": true,
      "original": {
        "value": "{font.space-grotesk-medium-weight-number.value}",
        "attributes": {
          "category": "font",
          "type": "weight"
        }
      },
      "name": "heading-weight-number",
      "path": [
        "heading",
        "weight-number"
      ]
    },
    "weight-strong-name": {
      "value": "Bold",
      "attributes": {
        "category": "font",
        "type": "name",
        "tailwind-name": "heading-weight-strong-name"
      },
      "filePath": "/Users/noah.waldner/dev/frontify/fondue/packages/tokens/src/tokens/alias.heading.ts",
      "isSource": true,
      "original": {
        "value": "{font.space-grotesk-bold-weight-name.value}",
        "attributes": {
          "category": "font",
          "type": "name"
        }
      },
      "name": "heading-weight-strong-name",
      "path": [
        "heading",
        "weight-strong-name"
      ]
    },
    "weight-strong-number": {
      "value": 700,
      "attributes": {
        "category": "font",
        "type": "weight",
        "tailwind-name": "heading-weight-strong-number"
      },
      "filePath": "/Users/noah.waldner/dev/frontify/fondue/packages/tokens/src/tokens/alias.heading.ts",
      "isSource": true,
      "original": {
        "value": "{font.space-grotesk-bold-weight-number.value}",
        "attributes": {
          "category": "font",
          "type": "weight"
        }
      },
      "name": "heading-weight-strong-number",
      "path": [
        "heading",
        "weight-strong-number"
      ]
    },
    "size-medium": {
      "value": "0.875rem",
      "attributes": {
        "category": "size",
        "type": "font",
        "tailwind-name": "heading-size-medium"
      },
      "filePath": "/Users/noah.waldner/dev/frontify/fondue/packages/tokens/src/tokens/alias.heading.ts",
      "isSource": true,
      "original": {
        "value": "{body.size-medium.value}",
        "attributes": {
          "category": "size",
          "type": "font"
        }
      },
      "name": "heading-size-medium",
      "path": [
        "heading",
        "size-medium"
      ]
    },
    "size-medium-line-height": {
      "value": "1rem",
      "attributes": {
        "category": "size",
        "type": "lineHeight",
        "tailwind-name": "heading-size-medium-line-height"
      },
      "filePath": "/Users/noah.waldner/dev/frontify/fondue/packages/tokens/src/tokens/alias.heading.ts",
      "isSource": true,
      "original": {
        "value": "1",
        "attributes": {
          "category": "size",
          "type": "lineHeight"
        }
      },
      "name": "heading-size-medium-line-height",
      "path": [
        "heading",
        "size-medium-line-height"
      ]
    },
    "size-large": {
      "value": "1rem",
      "attributes": {
        "category": "size",
        "type": "font",
        "tailwind-name": "heading-size-large"
      },
      "filePath": "/Users/noah.waldner/dev/frontify/fondue/packages/tokens/src/tokens/alias.heading.ts",
      "isSource": true,
      "original": {
        "value": "{body.size-large.value}",
        "attributes": {
          "category": "size",
          "type": "font"
        }
      },
      "name": "heading-size-large",
      "path": [
        "heading",
        "size-large"
      ]
    },
    "size-large-line-height": {
      "value": "1.25rem",
      "attributes": {
        "category": "size",
        "type": "lineHeight",
        "tailwind-name": "heading-size-large-line-height"
      },
      "filePath": "/Users/noah.waldner/dev/frontify/fondue/packages/tokens/src/tokens/alias.heading.ts",
      "isSource": true,
      "original": {
        "value": "{body.size-large-line-height.value}",
        "attributes": {
          "category": "size",
          "type": "lineHeight"
        }
      },
      "name": "heading-size-large-line-height",
      "path": [
        "heading",
        "size-large-line-height"
      ]
    },
    "size-x-large": {
      "value": "1.25rem",
      "attributes": {
        "category": "size",
        "type": "font",
        "tailwind-name": "heading-size-x-large"
      },
      "filePath": "/Users/noah.waldner/dev/frontify/fondue/packages/tokens/src/tokens/alias.heading.ts",
      "isSource": true,
      "original": {
        "value": 1.25,
        "attributes": {
          "category": "size",
          "type": "font"
        }
      },
      "name": "heading-size-x-large",
      "path": [
        "heading",
        "size-x-large"
      ]
    },
    "size-x-large-line-height": {
      "value": "1.5rem",
      "attributes": {
        "category": "size",
        "type": "lineHeight",
        "tailwind-name": "heading-size-x-large-line-height"
      },
      "filePath": "/Users/noah.waldner/dev/frontify/fondue/packages/tokens/src/tokens/alias.heading.ts",
      "isSource": true,
      "original": {
        "value": 1.5,
        "attributes": {
          "category": "size",
          "type": "lineHeight"
        }
      },
      "name": "heading-size-x-large-line-height",
      "path": [
        "heading",
        "size-x-large-line-height"
      ]
    },
    "size-xx-large": {
      "value": "1.5rem",
      "attributes": {
        "category": "size",
        "type": "font",
        "tailwind-name": "heading-size-xx-large"
      },
      "filePath": "/Users/noah.waldner/dev/frontify/fondue/packages/tokens/src/tokens/alias.heading.ts",
      "isSource": true,
      "original": {
        "value": 1.5,
        "attributes": {
          "category": "size",
          "type": "font"
        }
      },
      "name": "heading-size-xx-large",
      "path": [
        "heading",
        "size-xx-large"
      ]
    },
    "size-xx-large-line-height": {
      "value": "1.75rem",
      "attributes": {
        "category": "size",
        "type": "lineHeight",
        "tailwind-name": "heading-size-xx-large-line-height"
      },
      "filePath": "/Users/noah.waldner/dev/frontify/fondue/packages/tokens/src/tokens/alias.heading.ts",
      "isSource": true,
      "original": {
        "value": 1.75,
        "attributes": {
          "category": "size",
          "type": "lineHeight"
        }
      },
      "name": "heading-size-xx-large-line-height",
      "path": [
        "heading",
        "size-xx-large-line-height"
      ]
    },
    "medium": {
      "value": {
        "fontFamily": [
          "Diatype",
          "Space Grotesk Frontify"
        ],
        "fontSize": "0.875rem",
        "lineHeight": "1rem",
        "fontWeight": "Medium"
      },
      "attributes": {
        "category": "font",
        "type": "style",
        "target": "figma",
        "tailwind-name": "heading-medium"
      },
      "filePath": "/Users/noah.waldner/dev/frontify/fondue/packages/tokens/src/tokens/alias.heading.ts",
      "isSource": true,
      "original": {
        "value": {
          "fontFamily": "{heading.family.value}",
          "fontSize": "{heading.size-medium.value}",
          "lineHeight": "{heading.size-medium-line-height.value}",
          "fontWeight": "{heading.weight-name.value}"
        },
        "attributes": {
          "category": "font",
          "type": "style",
          "target": "figma"
        }
      },
      "name": "heading-medium",
      "path": [
        "heading",
        "medium"
      ]
    },
    "medium-strong": {
      "value": {
        "fontFamily": [
          "Diatype",
          "Space Grotesk Frontify"
        ],
        "fontSize": "0.875rem",
        "lineHeight": "1rem",
        "fontWeight": "Bold"
      },
      "attributes": {
        "category": "font",
        "type": "style",
        "target": "figma",
        "tailwind-name": "heading-medium-strong"
      },
      "filePath": "/Users/noah.waldner/dev/frontify/fondue/packages/tokens/src/tokens/alias.heading.ts",
      "isSource": true,
      "original": {
        "value": {
          "fontFamily": "{heading.family.value}",
          "fontSize": "{heading.size-medium.value}",
          "lineHeight": "{heading.size-medium-line-height.value}",
          "fontWeight": "{heading.weight-strong-name.value}"
        },
        "attributes": {
          "category": "font",
          "type": "style",
          "target": "figma"
        }
      },
      "name": "heading-medium-strong",
      "path": [
        "heading",
        "medium-strong"
      ]
    },
    "large": {
      "value": {
        "fontFamily": [
          "Diatype",
          "Space Grotesk Frontify"
        ],
        "fontSize": "1rem",
        "lineHeight": "1.25rem",
        "fontWeight": "Medium"
      },
      "attributes": {
        "category": "font",
        "type": "style",
        "target": "figma",
        "tailwind-name": "heading-large"
      },
      "filePath": "/Users/noah.waldner/dev/frontify/fondue/packages/tokens/src/tokens/alias.heading.ts",
      "isSource": true,
      "original": {
        "value": {
          "fontFamily": "{heading.family.value}",
          "fontSize": "{heading.size-large.value}",
          "lineHeight": "{heading.size-large-line-height.value}",
          "fontWeight": "{heading.weight-name.value}"
        },
        "attributes": {
          "category": "font",
          "type": "style",
          "target": "figma"
        }
      },
      "name": "heading-large",
      "path": [
        "heading",
        "large"
      ]
    },
    "large-strong": {
      "value": {
        "fontFamily": [
          "Diatype",
          "Space Grotesk Frontify"
        ],
        "fontSize": "1rem",
        "lineHeight": "1.25rem",
        "fontWeight": "Bold"
      },
      "attributes": {
        "category": "font",
        "type": "style",
        "target": "figma",
        "tailwind-name": "heading-large-strong"
      },
      "filePath": "/Users/noah.waldner/dev/frontify/fondue/packages/tokens/src/tokens/alias.heading.ts",
      "isSource": true,
      "original": {
        "value": {
          "fontFamily": "{heading.family.value}",
          "fontSize": "{heading.size-large.value}",
          "lineHeight": "{heading.size-large-line-height.value}",
          "fontWeight": "{heading.weight-strong-name.value}"
        },
        "attributes": {
          "category": "font",
          "type": "style",
          "target": "figma"
        }
      },
      "name": "heading-large-strong",
      "path": [
        "heading",
        "large-strong"
      ]
    },
    "x-large": {
      "value": {
        "fontFamily": [
          "Diatype",
          "Space Grotesk Frontify"
        ],
        "fontSize": "1.25rem",
        "lineHeight": "1.5rem",
        "fontWeight": "Medium"
      },
      "attributes": {
        "category": "font",
        "type": "style",
        "target": "figma",
        "tailwind-name": "heading-x-large"
      },
      "filePath": "/Users/noah.waldner/dev/frontify/fondue/packages/tokens/src/tokens/alias.heading.ts",
      "isSource": true,
      "original": {
        "value": {
          "fontFamily": "{heading.family.value}",
          "fontSize": "{heading.size-x-large.value}",
          "lineHeight": "{heading.size-x-large-line-height.value}",
          "fontWeight": "{heading.weight-name.value}"
        },
        "attributes": {
          "category": "font",
          "type": "style",
          "target": "figma"
        }
      },
      "name": "heading-x-large",
      "path": [
        "heading",
        "x-large"
      ]
    },
    "x-large-strong": {
      "value": {
        "fontFamily": [
          "Diatype",
          "Space Grotesk Frontify"
        ],
        "fontSize": "1.25rem",
        "lineHeight": "1.5rem",
        "fontWeight": "Bold"
      },
      "attributes": {
        "category": "font",
        "type": "style",
        "target": "figma",
        "tailwind-name": "heading-x-large-strong"
      },
      "filePath": "/Users/noah.waldner/dev/frontify/fondue/packages/tokens/src/tokens/alias.heading.ts",
      "isSource": true,
      "original": {
        "value": {
          "fontFamily": "{heading.family.value}",
          "fontSize": "{heading.size-x-large.value}",
          "lineHeight": "{heading.size-x-large-line-height.value}",
          "fontWeight": "{heading.weight-strong-name.value}"
        },
        "attributes": {
          "category": "font",
          "type": "style",
          "target": "figma"
        }
      },
      "name": "heading-x-large-strong",
      "path": [
        "heading",
        "x-large-strong"
      ]
    },
    "xx-large": {
      "value": {
        "fontFamily": [
          "Diatype",
          "Space Grotesk Frontify"
        ],
        "fontSize": "1.5rem",
        "lineHeight": "1.75rem",
        "fontWeight": "Medium"
      },
      "attributes": {
        "category": "font",
        "type": "style",
        "target": "figma",
        "tailwind-name": "heading-xx-large"
      },
      "filePath": "/Users/noah.waldner/dev/frontify/fondue/packages/tokens/src/tokens/alias.heading.ts",
      "isSource": true,
      "original": {
        "value": {
          "fontFamily": "{heading.family.value}",
          "fontSize": "{heading.size-xx-large.value}",
          "lineHeight": "{heading.size-xx-large-line-height.value}",
          "fontWeight": "{heading.weight-name.value}"
        },
        "attributes": {
          "category": "font",
          "type": "style",
          "target": "figma"
        }
      },
      "name": "heading-xx-large",
      "path": [
        "heading",
        "xx-large"
      ]
    },
    "xx-large-strong": {
      "value": {
        "fontFamily": [
          "Diatype",
          "Space Grotesk Frontify"
        ],
        "fontSize": "1.5rem",
        "lineHeight": "1.75rem",
        "fontWeight": "Bold"
      },
      "attributes": {
        "category": "font",
        "type": "style",
        "target": "figma",
        "tailwind-name": "heading-xx-large-strong"
      },
      "filePath": "/Users/noah.waldner/dev/frontify/fondue/packages/tokens/src/tokens/alias.heading.ts",
      "isSource": true,
      "original": {
        "value": {
          "fontFamily": "{heading.family.value}",
          "fontSize": "{heading.size-xx-large.value}",
          "lineHeight": "{heading.size-xx-large-line-height.value}",
          "fontWeight": "{heading.weight-strong-name.value}"
        },
        "attributes": {
          "category": "font",
          "type": "style",
          "target": "figma"
        }
      },
      "name": "heading-xx-large-strong",
      "path": [
        "heading",
        "xx-large-strong"
      ]
    }
  },
  "line": {
    "width": {
      "value": "0.063rem",
      "attributes": {
        "category": "size",
        "type": "lineWidth",
        "tailwind-name": "line-width"
      },
      "filePath": "/Users/noah.waldner/dev/frontify/fondue/packages/tokens/src/tokens/alias.line.ts",
      "isSource": true,
      "original": {
        "value": 0.063,
        "attributes": {
          "category": "size",
          "type": "lineWidth"
        }
      },
      "name": "line-width",
      "path": [
        "line",
        "width"
      ]
    },
    "width-large": {
      "value": "0.125rem",
      "attributes": {
        "category": "size",
        "type": "lineWidth",
        "tailwind-name": "line-width-large"
      },
      "filePath": "/Users/noah.waldner/dev/frontify/fondue/packages/tokens/src/tokens/alias.line.ts",
      "isSource": true,
      "original": {
        "value": 0.125,
        "attributes": {
          "category": "size",
          "type": "lineWidth"
        }
      },
      "name": "line-width-large",
      "path": [
        "line",
        "width-large"
      ]
    }
  },
  "radius": {
    "_": {
      "value": "0.25rem",
      "attributes": {
        "category": "size",
        "type": "borderRadius",
        "tailwind-name": "radius"
      },
      "filePath": "/Users/noah.waldner/dev/frontify/fondue/packages/tokens/src/tokens/alias.radius.ts",
      "isSource": true,
      "original": {
        "value": 0.25,
        "attributes": {
          "category": "size",
          "type": "borderRadius"
        }
      },
      "name": "radius",
      "path": [
        "radius",
        "_"
      ]
    },
    "small": {
      "value": "0.125rem",
      "attributes": {
        "category": "size",
        "type": "borderRadius",
        "tailwind-name": "radius-small"
      },
      "filePath": "/Users/noah.waldner/dev/frontify/fondue/packages/tokens/src/tokens/alias.radius.ts",
      "isSource": true,
      "original": {
        "value": 0.125,
        "attributes": {
          "category": "size",
          "type": "borderRadius"
        }
      },
      "name": "radius-small",
      "path": [
        "radius",
        "small"
      ]
    },
    "large": {
      "value": "0.5rem",
      "attributes": {
        "category": "size",
        "type": "borderRadius",
        "tailwind-name": "radius-large"
      },
      "filePath": "/Users/noah.waldner/dev/frontify/fondue/packages/tokens/src/tokens/alias.radius.ts",
      "isSource": true,
      "original": {
        "value": 0.5,
        "attributes": {
          "category": "size",
          "type": "borderRadius"
        }
      },
      "name": "radius-large",
      "path": [
        "radius",
        "large"
      ]
    },
    "x-large": {
      "value": "0.75rem",
      "attributes": {
        "category": "size",
        "type": "borderRadius",
        "tailwind-name": "radius-x-large"
      },
      "filePath": "/Users/noah.waldner/dev/frontify/fondue/packages/tokens/src/tokens/alias.radius.ts",
      "isSource": true,
      "original": {
        "value": 0.75,
        "attributes": {
          "category": "size",
          "type": "borderRadius"
        }
      },
      "name": "radius-x-large",
      "path": [
        "radius",
        "x-large"
      ]
    }
  },
  "shadow": {
    "matrix": {
      "value": "0.1875rem 0rem 0.625rem 0rem rgba(8, 8, 8, 0.15)",
      "attributes": {
        "type": "matrix",
        "category": "shadow",
        "tailwind-name": "shadow-matrix"
      },
      "filePath": "/Users/noah.waldner/dev/frontify/fondue/packages/tokens/src/tokens/alias.shadow.ts",
      "isSource": true,
      "original": {
        "value": "{shadow.offset-y.value} {shadow.offset-x.value} {shadow.blur.value} {shadow.spread.value} {shadow.color.value}",
        "attributes": {
          "type": "matrix"
        }
      },
      "name": "shadow-matrix",
      "path": [
        "shadow",
        "matrix"
      ]
    },
    "offset-x": {
      "value": "0rem",
      "attributes": {
        "category": "size",
        "type": "shadowOffset",
        "item": "x",
        "tailwind-name": "shadow-offset-x"
      },
      "filePath": "/Users/noah.waldner/dev/frontify/fondue/packages/tokens/src/tokens/alias.shadow.ts",
      "isSource": true,
      "original": {
        "value": 0,
        "attributes": {
          "category": "size",
          "type": "shadowOffset",
          "item": "x"
        }
      },
      "name": "shadow-offset-x",
      "path": [
        "shadow",
        "offset-x"
      ]
    },
    "offset-y": {
      "value": "0.1875rem",
      "attributes": {
        "category": "size",
        "type": "shadowOffset",
        "item": "y",
        "tailwind-name": "shadow-offset-y"
      },
      "filePath": "/Users/noah.waldner/dev/frontify/fondue/packages/tokens/src/tokens/alias.shadow.ts",
      "isSource": true,
      "original": {
        "value": 0.1875,
        "attributes": {
          "category": "size",
          "type": "shadowOffset",
          "item": "y"
        }
      },
      "name": "shadow-offset-y",
      "path": [
        "shadow",
        "offset-y"
      ]
    },
    "spread": {
      "value": "0rem",
      "attributes": {
        "category": "size",
        "type": "shadowSpread",
        "tailwind-name": "shadow-spread"
      },
      "filePath": "/Users/noah.waldner/dev/frontify/fondue/packages/tokens/src/tokens/alias.shadow.ts",
      "isSource": true,
      "original": {
        "value": 0,
        "attributes": {
          "category": "size",
          "type": "shadowSpread"
        }
      },
      "name": "shadow-spread",
      "path": [
        "shadow",
        "spread"
      ]
    },
    "blur": {
      "value": "0.625rem",
      "attributes": {
        "category": "size",
        "type": "shadowBlur",
        "tailwind-name": "shadow-blur"
      },
      "filePath": "/Users/noah.waldner/dev/frontify/fondue/packages/tokens/src/tokens/alias.shadow.ts",
      "isSource": true,
      "original": {
        "value": 0.625,
        "attributes": {
          "category": "size",
          "type": "shadowBlur"
        }
      },
      "name": "shadow-blur",
      "path": [
        "shadow",
        "blur"
      ]
    },
    "top-matrix": {
      "value": "-0.625rem 0rem 0.625rem -0.3125rem rgba(8, 8, 8, 0.15)",
      "attributes": {
        "type": "matrix",
        "category": "shadow",
        "tailwind-name": "shadow-top-matrix"
      },
      "filePath": "/Users/noah.waldner/dev/frontify/fondue/packages/tokens/src/tokens/alias.shadow.ts",
      "isSource": true,
      "original": {
        "value": "{shadow.top-offset-y.value} {shadow.top-offset-x.value} {shadow.blur.value} {shadow.top-spread.value} {shadow.color.value}",
        "attributes": {
          "type": "matrix"
        }
      },
      "name": "shadow-top-matrix",
      "path": [
        "shadow",
        "top-matrix"
      ]
    },
    "top-offset-x": {
      "value": "0rem",
      "attributes": {
        "category": "size",
        "type": "shadowOffset",
        "item": "x",
        "tailwind-name": "shadow-top-offset-x"
      },
      "filePath": "/Users/noah.waldner/dev/frontify/fondue/packages/tokens/src/tokens/alias.shadow.ts",
      "isSource": true,
      "original": {
        "value": "{shadow.offset-x.value}",
        "attributes": {
          "category": "size",
          "type": "shadowOffset",
          "item": "x"
        }
      },
      "name": "shadow-top-offset-x",
      "path": [
        "shadow",
        "top-offset-x"
      ]
    },
    "top-offset-y": {
      "value": "-0.625rem",
      "attributes": {
        "category": "size",
        "type": "shadowOffset",
        "item": "y",
        "tailwind-name": "shadow-top-offset-y"
      },
      "filePath": "/Users/noah.waldner/dev/frontify/fondue/packages/tokens/src/tokens/alias.shadow.ts",
      "isSource": true,
      "original": {
        "value": -0.625,
        "attributes": {
          "category": "size",
          "type": "shadowOffset",
          "item": "y"
        }
      },
      "name": "shadow-top-offset-y",
      "path": [
        "shadow",
        "top-offset-y"
      ]
    },
    "top-spread": {
      "value": "-0.3125rem",
      "attributes": {
        "category": "size",
        "type": "shadowSpread",
        "tailwind-name": "shadow-top-spread"
      },
      "filePath": "/Users/noah.waldner/dev/frontify/fondue/packages/tokens/src/tokens/alias.shadow.ts",
      "isSource": true,
      "original": {
        "value": -0.3125,
        "attributes": {
          "category": "size",
          "type": "shadowSpread"
        }
      },
      "name": "shadow-top-spread",
      "path": [
        "shadow",
        "top-spread"
      ]
    },
    "bottom-matrix": {
      "value": "0.625rem 0rem 0.625rem -0.3125rem rgba(8, 8, 8, 0.15)",
      "attributes": {
        "type": "matrix",
        "category": "shadow",
        "tailwind-name": "shadow-bottom-matrix"
      },
      "filePath": "/Users/noah.waldner/dev/frontify/fondue/packages/tokens/src/tokens/alias.shadow.ts",
      "isSource": true,
      "original": {
        "value": "{shadow.bottom-offset-y.value} {shadow.bottom-offset-x.value} {shadow.blur.value} {shadow.bottom-spread.value} {shadow.color.value}",
        "attributes": {
          "type": "matrix"
        }
      },
      "name": "shadow-bottom-matrix",
      "path": [
        "shadow",
        "bottom-matrix"
      ]
    },
    "bottom-offset-x": {
      "value": "0rem",
      "attributes": {
        "category": "size",
        "type": "shadowOffset",
        "item": "x",
        "tailwind-name": "shadow-bottom-offset-x"
      },
      "filePath": "/Users/noah.waldner/dev/frontify/fondue/packages/tokens/src/tokens/alias.shadow.ts",
      "isSource": true,
      "original": {
        "value": "{shadow.offset-x.value}",
        "attributes": {
          "category": "size",
          "type": "shadowOffset",
          "item": "x"
        }
      },
      "name": "shadow-bottom-offset-x",
      "path": [
        "shadow",
        "bottom-offset-x"
      ]
    },
    "bottom-offset-y": {
      "value": "0.625rem",
      "attributes": {
        "category": "size",
        "type": "shadowOffset",
        "item": "y",
        "tailwind-name": "shadow-bottom-offset-y"
      },
      "filePath": "/Users/noah.waldner/dev/frontify/fondue/packages/tokens/src/tokens/alias.shadow.ts",
      "isSource": true,
      "original": {
        "value": 0.625,
        "attributes": {
          "category": "size",
          "type": "shadowOffset",
          "item": "y"
        }
      },
      "name": "shadow-bottom-offset-y",
      "path": [
        "shadow",
        "bottom-offset-y"
      ]
    },
    "bottom-spread": {
      "value": "-0.3125rem",
      "attributes": {
        "category": "size",
        "type": "shadowSpread",
        "tailwind-name": "shadow-bottom-spread"
      },
      "filePath": "/Users/noah.waldner/dev/frontify/fondue/packages/tokens/src/tokens/alias.shadow.ts",
      "isSource": true,
      "original": {
        "value": -0.3125,
        "attributes": {
          "category": "size",
          "type": "shadowSpread"
        }
      },
      "name": "shadow-bottom-spread",
      "path": [
        "shadow",
        "bottom-spread"
      ]
    },
    "large-matrix": {
      "value": "1.5625rem 0rem 5rem 0rem rgba(8, 8, 8, 0.2)",
      "attributes": {
        "type": "matrix",
        "category": "shadow",
        "tailwind-name": "shadow-large-matrix"
      },
      "filePath": "/Users/noah.waldner/dev/frontify/fondue/packages/tokens/src/tokens/alias.shadow.ts",
      "isSource": true,
      "original": {
        "value": "{shadow.large-offset-y.value} {shadow.large-offset-x.value} {shadow.large-blur.value} {shadow.large-spread.value} {shadow.large-color.value}",
        "attributes": {
          "type": "matrix"
        }
      },
      "name": "shadow-large-matrix",
      "path": [
        "shadow",
        "large-matrix"
      ]
    },
    "large-offset-x": {
      "value": "0rem",
      "attributes": {
        "category": "size",
        "type": "shadowOffset",
        "item": "x",
        "tailwind-name": "shadow-large-offset-x"
      },
      "filePath": "/Users/noah.waldner/dev/frontify/fondue/packages/tokens/src/tokens/alias.shadow.ts",
      "isSource": true,
      "original": {
        "value": 0,
        "attributes": {
          "category": "size",
          "type": "shadowOffset",
          "item": "x"
        }
      },
      "name": "shadow-large-offset-x",
      "path": [
        "shadow",
        "large-offset-x"
      ]
    },
    "large-offset-y": {
      "value": "1.5625rem",
      "attributes": {
        "category": "size",
        "type": "shadowOffset",
        "item": "y",
        "tailwind-name": "shadow-large-offset-y"
      },
      "filePath": "/Users/noah.waldner/dev/frontify/fondue/packages/tokens/src/tokens/alias.shadow.ts",
      "isSource": true,
      "original": {
        "value": 1.5625,
        "attributes": {
          "category": "size",
          "type": "shadowOffset",
          "item": "y"
        }
      },
      "name": "shadow-large-offset-y",
      "path": [
        "shadow",
        "large-offset-y"
      ]
    },
    "large-spread": {
      "value": "0rem",
      "attributes": {
        "category": "size",
        "type": "shadowSpread",
        "tailwind-name": "shadow-large-spread"
      },
      "filePath": "/Users/noah.waldner/dev/frontify/fondue/packages/tokens/src/tokens/alias.shadow.ts",
      "isSource": true,
      "original": {
        "value": 0,
        "attributes": {
          "category": "size",
          "type": "shadowSpread"
        }
      },
      "name": "shadow-large-spread",
      "path": [
        "shadow",
        "large-spread"
      ]
    },
    "large-blur": {
      "value": "5rem",
      "attributes": {
        "category": "size",
        "type": "shadowBlur",
        "tailwind-name": "shadow-large-blur"
      },
      "filePath": "/Users/noah.waldner/dev/frontify/fondue/packages/tokens/src/tokens/alias.shadow.ts",
      "isSource": true,
      "original": {
        "value": 5,
        "attributes": {
          "category": "size",
          "type": "shadowBlur"
        }
      },
      "name": "shadow-large-blur",
      "path": [
        "shadow",
        "large-blur"
      ]
    },
    "_": {
      "value": {
        "x": "0rem",
        "y": "0.1875rem",
        "blur": "0.625rem",
        "spread": "0rem",
        "color": "rgba(8, 8, 8, 0.15)"
      },
      "attributes": {
        "category": "shadow",
        "type": "style",
        "target": "figma",
        "tailwind-name": "shadow"
      },
      "filePath": "/Users/noah.waldner/dev/frontify/fondue/packages/tokens/src/tokens/alias.shadow.ts",
      "isSource": true,
      "original": {
        "value": {
          "x": "{shadow.offset-x.value}",
          "y": "{shadow.offset-y.value}",
          "blur": "{shadow.blur.value}",
          "spread": "{shadow.spread.value}",
          "color": "{shadow.color.value}"
        },
        "attributes": {
          "category": "shadow",
          "type": "style",
          "target": "figma"
        }
      },
      "name": "shadow",
      "path": [
        "shadow",
        "_"
      ]
    },
    "top": {
      "value": {
        "x": "0rem",
        "y": "-0.625rem",
        "blur": "0.625rem",
        "spread": "-0.3125rem",
        "color": "rgba(8, 8, 8, 0.15)"
      },
      "attributes": {
        "category": "shadow",
        "type": "style",
        "target": "figma",
        "tailwind-name": "shadow-top"
      },
      "filePath": "/Users/noah.waldner/dev/frontify/fondue/packages/tokens/src/tokens/alias.shadow.ts",
      "isSource": true,
      "original": {
        "value": {
          "x": "{shadow.top-offset-x.value}",
          "y": "{shadow.top-offset-y.value}",
          "blur": "{shadow.blur.value}",
          "spread": "{shadow.top-spread.value}",
          "color": "{shadow.color.value}"
        },
        "attributes": {
          "category": "shadow",
          "type": "style",
          "target": "figma"
        }
      },
      "name": "shadow-top",
      "path": [
        "shadow",
        "top"
      ]
    },
    "bottom": {
      "value": {
        "x": "0rem",
        "y": "0.625rem",
        "blur": "0.625rem",
        "spread": "-0.3125rem",
        "color": "rgba(8, 8, 8, 0.15)"
      },
      "attributes": {
        "category": "shadow",
        "type": "style",
        "target": "figma",
        "tailwind-name": "shadow-bottom"
      },
      "filePath": "/Users/noah.waldner/dev/frontify/fondue/packages/tokens/src/tokens/alias.shadow.ts",
      "isSource": true,
      "original": {
        "value": {
          "x": "{shadow.bottom-offset-x.value}",
          "y": "{shadow.bottom-offset-y.value}",
          "blur": "{shadow.blur.value}",
          "spread": "{shadow.bottom-spread.value}",
          "color": "{shadow.color.value}"
        },
        "attributes": {
          "category": "shadow",
          "type": "style",
          "target": "figma"
        }
      },
      "name": "shadow-bottom",
      "path": [
        "shadow",
        "bottom"
      ]
    },
    "big": {
      "value": {
        "x": "0rem",
        "y": "1.5625rem",
        "blur": "5rem",
        "spread": "0rem",
        "color": "rgba(8, 8, 8, 0.2)"
      },
      "attributes": {
        "category": "shadow",
        "type": "style",
        "target": "figma",
        "tailwind-name": "shadow-big"
      },
      "filePath": "/Users/noah.waldner/dev/frontify/fondue/packages/tokens/src/tokens/alias.shadow.ts",
      "isSource": true,
      "original": {
        "value": {
          "x": "{shadow.large-offset-x.value}",
          "y": "{shadow.large-offset-y.value}",
          "blur": "{shadow.large-blur.value}",
          "spread": "{shadow.large-spread.value}",
          "color": "{shadow.large-color.value}"
        },
        "attributes": {
          "category": "shadow",
          "type": "style",
          "target": "figma"
        }
      },
      "name": "shadow-big",
      "path": [
        "shadow",
        "big"
      ]
    }
  },
  "space": {
    "xxs": {
      "value": "0.25rem",
      "attributes": {
        "category": "size",
        "type": "spacing",
        "tailwind-name": "space-xxs"
      },
      "filePath": "/Users/noah.waldner/dev/frontify/fondue/packages/tokens/src/tokens/alias.space.ts",
      "isSource": true,
      "original": {
        "value": 0.25,
        "attributes": {
          "category": "size",
          "type": "spacing"
        }
      },
      "name": "space-xxs",
      "path": [
        "space",
        "xxs"
      ]
    },
    "xs": {
      "value": "0.5rem",
      "attributes": {
        "category": "size",
        "type": "spacing",
        "tailwind-name": "space-xs"
      },
      "filePath": "/Users/noah.waldner/dev/frontify/fondue/packages/tokens/src/tokens/alias.space.ts",
      "isSource": true,
      "original": {
        "value": 0.5,
        "attributes": {
          "category": "size",
          "type": "spacing"
        }
      },
      "name": "space-xs",
      "path": [
        "space",
        "xs"
      ]
    },
    "s": {
      "value": "0.75rem",
      "attributes": {
        "category": "size",
        "type": "spacing",
        "tailwind-name": "space-s"
      },
      "filePath": "/Users/noah.waldner/dev/frontify/fondue/packages/tokens/src/tokens/alias.space.ts",
      "isSource": true,
      "original": {
        "value": 0.75,
        "attributes": {
          "category": "size",
          "type": "spacing"
        }
      },
      "name": "space-s",
      "path": [
        "space",
        "s"
      ]
    },
    "m": {
      "value": "1rem",
      "attributes": {
        "category": "size",
        "type": "spacing",
        "tailwind-name": "space-m"
      },
      "filePath": "/Users/noah.waldner/dev/frontify/fondue/packages/tokens/src/tokens/alias.space.ts",
      "isSource": true,
      "original": {
        "value": 1,
        "attributes": {
          "category": "size",
          "type": "spacing"
        }
      },
      "name": "space-m",
      "path": [
        "space",
        "m"
      ]
    },
    "l": {
      "value": "1.5rem",
      "attributes": {
        "category": "size",
        "type": "spacing",
        "tailwind-name": "space-l"
      },
      "filePath": "/Users/noah.waldner/dev/frontify/fondue/packages/tokens/src/tokens/alias.space.ts",
      "isSource": true,
      "original": {
        "value": 1.5,
        "attributes": {
          "category": "size",
          "type": "spacing"
        }
      },
      "name": "space-l",
      "path": [
        "space",
        "l"
      ]
    },
    "xl": {
      "value": "2rem",
      "attributes": {
        "category": "size",
        "type": "spacing",
        "tailwind-name": "space-xl"
      },
      "filePath": "/Users/noah.waldner/dev/frontify/fondue/packages/tokens/src/tokens/alias.space.ts",
      "isSource": true,
      "original": {
        "value": 2,
        "attributes": {
          "category": "size",
          "type": "spacing"
        }
      },
      "name": "space-xl",
      "path": [
        "space",
        "xl"
      ]
    },
    "xxl": {
      "value": "2.5rem",
      "attributes": {
        "category": "size",
        "type": "spacing",
        "tailwind-name": "space-xxl"
      },
      "filePath": "/Users/noah.waldner/dev/frontify/fondue/packages/tokens/src/tokens/alias.space.ts",
      "isSource": true,
      "original": {
        "value": 2.5,
        "attributes": {
          "category": "size",
          "type": "spacing"
        }
      },
      "name": "space-xxl",
      "path": [
        "space",
        "xxl"
      ]
    }
  }
}
